baosight/__init__.py
baosight/cli/__init__.py
baosight/cli/cmd_admin.py
baosight/cli/gl_runner.py
baosight/cli/main.py
baosight/gitlab_tools/__init__.py
baosight/gitlab_tools/config.py
baosight/gitlab_tools/core.py
baosight/gitlab_tools/gitlab_runner.py
baosight/gitlab_tools/gitlab_runner_config_generator.py
baosight/gui/__init__.py
baosight/gui/gl_runner_installer.py
baosight/test/__init__.py
baosight/test/main.py
baosight/tools/__init__.py
baosight/tools/utils.py
baosight-0.0.14.dist-info/LICENSE
baosight-0.0.14.dist-info/METADATA
baosight-0.0.14.dist-info/WHEEL
baosight-0.0.14.dist-info/entry_points.txt
baosight-0.0.14.dist-info/top_level.txt
baosight-0.0.14.dist-info/RECORD
