Metadata-Version: 2.1
Name: baosight
Version: 0.0.14
Summary: baosight tools
Home-page: https://cuddlebugs.asia
Author: Hao Zhao
Author-email: 601095001@qq.com
License: OSI Approved :: MIT License
Platform: Linux/Windows
Classifier: Programming Language :: Python :: 3
Classifier: License :: OSI Approved :: MIT License
Classifier: Operating System :: OS Independent
Requires-Python: >=3.8
License-File: LICENSE
Requires-Dist: python-gitlab ==4.5.0
Requires-Dist: requests ==2.31.0
